LICENSE
MANIFEST.in
README.md
requirements.txt
setup.cfg
setup.py
src/isodata/__init__.py
src/isodata/connector.py
src/isodata/sessions.py
src/isodata/utils.py
src/isodata/ercot/__init__.py
src/isodata/ercot/connector.py
src/isodata/pjm/__init__.py
src/isodata/pjm/connector.py
src/isodata/pjm/constants.py
src/isodata/pjm/helper.py
src/isodata/pjm/query/QueryASBilaterals.py
src/isodata/pjm/query/QueryActiveSubzone.py
src/isodata/pjm/query/QueryAllDSRScheduleDetail.py
src/isodata/pjm/query/QueryAllDSRScheduleSelection.py
src/isodata/pjm/query/QueryAllScheduleAvailabilityUpdate.py
src/isodata/pjm/query/QueryAllScheduleDetail.py
src/isodata/pjm/query/QueryAllScheduleDetailUpdate.py
src/isodata/pjm/query/QueryAllScheduleGasNomination.py
src/isodata/pjm/query/QueryAllScheduleOffer.py
src/isodata/pjm/query/QueryAllScheduleRestriction.py
src/isodata/pjm/query/QueryAllScheduleSelection.py
src/isodata/pjm/query/QueryAllScheduleUpdate.py
src/isodata/pjm/query/QueryBidNodes.py
src/isodata/pjm/query/QueryBindingLimits.py
src/isodata/pjm/query/QueryByTransaction.py
src/isodata/pjm/query/QueryDA30MinuteReserveResults.py
src/isodata/pjm/query/QueryDANonSynchronizedReserveAward.py
src/isodata/pjm/query/QueryDAPrimaryReserveResults.py
src/isodata/pjm/query/QueryDASchedMW.py
src/isodata/pjm/query/QueryDASecondaryReserveAward.py
src/isodata/pjm/query/QueryDASynchronizedReserveAward.py
src/isodata/pjm/query/QueryDASynchronizedReserveResults.py
src/isodata/pjm/query/QueryDSRDASecondaryReserveAward.py
src/isodata/pjm/query/QueryDSRDASynchronizedReserveAward.py
src/isodata/pjm/query/QueryDSRDetail.py
src/isodata/pjm/query/QueryDSRRTSecondaryReserveAward.py
src/isodata/pjm/query/QueryDSRRTSynchronizedReserveAward.py
src/isodata/pjm/query/QueryDSRRegistration.py
src/isodata/pjm/query/QueryDSRRegulationAward.py
src/isodata/pjm/query/QueryDSRRegulationOffer.py
src/isodata/pjm/query/QueryDSRRegulationUpdate.py
src/isodata/pjm/query/QueryDSRSRREGAward.py
src/python_isodata.egg-info/PKG-INFO
src/python_isodata.egg-info/SOURCES.txt
src/python_isodata.egg-info/dependency_links.txt
src/python_isodata.egg-info/requires.txt
src/python_isodata.egg-info/top_level.txt
