Metadata-Version: 2.1
Name: python-isodata
Version: 0.0.15
Summary: Energy Market downloading tools
Home-page: https://github.com/CaffeineLab/isodata
Author: Caffeine Lab, LLC.
Author-email: glenn@caffeinelab.com
License: GNU General Public License v3.0
License-File: LICENSE
Requires-Dist: loguru
Requires-Dist: requests
Requires-Dist: python-dateutil
Requires-Dist: lxml
